code2claude/__init__.py
code2claude/consolidate.py
code2claude-0.3.0.dist-info/LICENSE
code2claude-0.3.0.dist-info/METADATA
code2claude-0.3.0.dist-info/WHEEL
code2claude-0.3.0.dist-info/entry_points.txt
code2claude-0.3.0.dist-info/top_level.txt
code2claude-0.3.0.dist-info/RECORD
