Metadata-Version: 2.1
Name: code2claude
Version: 0.3.0
Summary: A Python tool that consolidates code from a repository into a unified format for AI-assisted analysis and manipulation.
Home-page: https://github.com/ad3002/code2claude
Author: Aleksey Komissarov
Author-email: ad3002@gmail.com
License: BSD
Classifier: Development Status :: 4 - Beta
Classifier: Environment :: Console
Classifier: Intended Audience :: Science/Research
Classifier: License :: OSI Approved :: MIT License
Classifier: Operating System :: OS Independent
Classifier: Programming Language :: Python
Classifier: Topic :: Scientific/Engineering :: Artificial Intelligence
Requires-Python: >=3.6
License-File: LICENSE
